gpg_client/__init__.py
gpg_client/gpgclient.py
gpgclient-0.0.6.dist-info/METADATA
gpgclient-0.0.6.dist-info/WHEEL
gpgclient-0.0.6.dist-info/top_level.txt
gpgclient-0.0.6.dist-info/RECORD
