Metadata-Version: 2.1
Name: gpgclient
Version: 0.0.6
Summary: GPG Wrapper Client for leveraging gpg functionality with gcs
Home-page: UNKNOWN
Author: chris pearce
Author-email: christopher.pearce@bt.com
Maintainer: cpearce
Maintainer-email: christopher.pearce@bt.com
License: UNKNOWN
Platform: UNKNOWN
Requires-Dist: google-cloud-storage (>=1.42.3)
Requires-Dist: python-gnupg (>=0.4.8)
Requires-Dist: google-api-python-client (>=2.27.0)
